cratedb_fivetran_destination/__init__.py
cratedb_fivetran_destination/__main__.py
cratedb_fivetran_destination/cli.py
cratedb_fivetran_destination/dictx.py
cratedb_fivetran_destination/engine.py
cratedb_fivetran_destination/main.py
cratedb_fivetran_destination/model.py
cratedb_fivetran_destination/py.typed
cratedb_fivetran_destination/read_csv.py
cratedb_fivetran_destination/schema_migration_helper.py
cratedb_fivetran_destination/testing.py
cratedb_fivetran_destination/util.py
cratedb_fivetran_destination-0.0.4.dist-info/licenses/LICENSE
fivetran_sdk/__init__.py
fivetran_sdk/common_pb2.py
fivetran_sdk/common_pb2.pyi
fivetran_sdk/common_pb2_grpc.py
fivetran_sdk/connector_sdk_pb2.py
fivetran_sdk/connector_sdk_pb2.pyi
fivetran_sdk/connector_sdk_pb2_grpc.py
fivetran_sdk/destination_sdk_pb2.py
fivetran_sdk/destination_sdk_pb2.pyi
fivetran_sdk/destination_sdk_pb2_grpc.py
cratedb_fivetran_destination-0.0.4.dist-info/METADATA
cratedb_fivetran_destination-0.0.4.dist-info/WHEEL
cratedb_fivetran_destination-0.0.4.dist-info/entry_points.txt
cratedb_fivetran_destination-0.0.4.dist-info/top_level.txt
cratedb_fivetran_destination-0.0.4.dist-info/RECORD
