Metadata-Version: 2.4
Name: cratedb-fivetran-destination
Version: 0.0.4
Summary: CrateDB Fivetran Destination
Author-email: CrateDB Developers <office@crate.io>
License-Expression: Apache-2.0
Project-URL: Release Notes, https://github.com/crate/cratedb-fivetran-destination/releases
Project-URL: Repository, https://github.com/crate/cratedb-fivetran-destination
Keywords: cdc,cratedb,database destination adapter,fivetran
Classifier: Development Status :: 4 - Beta
Classifier: Environment :: Console
Classifier: Environment :: No Input/Output (Daemon)
Classifier: Environment :: Plugins
Classifier: Environment :: Web Environment
Classifier: Intended Audience :: Customer Service
Classifier: Intended Audience :: Developers
Classifier: Intended Audience :: Education
Classifier: Intended Audience :: End Users/Desktop
Classifier: Intended Audience :: Information Technology
Classifier: Intended Audience :: Science/Research
Classifier: Operating System :: MacOS
Classifier: Operating System :: POSIX
Classifier: Operating System :: Unix
Classifier: Programming Language :: ML
Classifier: Programming Language :: Python
Classifier: Programming Language :: Python :: 3 :: Only
Classifier: Programming Language :: Python :: 3.9
Classifier: Programming Language :: Python :: 3.10
Classifier: Programming Language :: Python :: 3.11
Classifier: Programming Language :: Python :: 3.12
Classifier: Programming Language :: Python :: 3.13
Classifier: Programming Language :: Python :: 3.14
Classifier: Topic :: Communications
Classifier: Topic :: Database
Classifier: Topic :: Documentation
Classifier: Topic :: Internet
Classifier: Topic :: Internet :: WWW/HTTP :: Indexing/Search
Classifier: Topic :: Printing
Classifier: Topic :: Scientific/Engineering :: Artificial Intelligence
Classifier: Topic :: Scientific/Engineering :: Human Machine Interfaces
Classifier: Topic :: Scientific/Engineering :: Image Processing
Classifier: Topic :: Scientific/Engineering :: Image Recognition
Classifier: Topic :: Scientific/Engineering :: Information Analysis
Classifier: Topic :: Scientific/Engineering :: Interface Engine/Protocol Translator
Classifier: Topic :: Software Development :: Code Generators
Classifier: Topic :: Software Development :: Libraries
Classifier: Topic :: Software Development :: Libraries :: Application Frameworks
Classifier: Topic :: Software Development :: Pre-processors
Classifier: Topic :: System :: Archiving
Classifier: Topic :: Text Processing
Classifier: Topic :: Text Processing :: Filters
Classifier: Topic :: Text Processing :: Indexing
Classifier: Topic :: Text Processing :: Linguistic
Classifier: Topic :: Utilities
Requires-Python: >=3.9
License-File: LICENSE
Requires-Dist: attrs<26
Requires-Dist: click<9
Requires-Dist: google<3.1
Requires-Dist: grpcio<1.77
Requires-Dist: grpcio-tools<1.77
Requires-Dist: protobuf<6.34
Requires-Dist: pycryptodome<3.24
Requires-Dist: python-dateutil<2.10
Requires-Dist: sqlalchemy-cratedb==0.42.0.dev2
Requires-Dist: toolz<2
Requires-Dist: zstandard<0.26
Provides-Extra: develop
Requires-Dist: mypy<1.20; extra == "develop"
Requires-Dist: poethepoet<1; extra == "develop"
Requires-Dist: pyproject-fmt<3; extra == "develop"
Requires-Dist: ruff<0.15; extra == "develop"
Requires-Dist: validate-pyproject<1; extra == "develop"
Provides-Extra: release
Requires-Dist: build<2; extra == "release"
Requires-Dist: poethepoet<1; extra == "release"
Requires-Dist: pyinstaller<7; extra == "release"
Requires-Dist: twine<7; extra == "release"
Provides-Extra: test
Requires-Dist: coverage<8; extra == "test"
Requires-Dist: pretend<2; extra == "test"
Requires-Dist: pytest<10; extra == "test"
Requires-Dist: pytest-mock<4; extra == "test"
Dynamic: license-file
